pipyadc/ADS1256_default_config.py
pipyadc/ADS1256_definitions.py
pipyadc/__init__.py
pipyadc/_version.py
pipyadc/pipyadc.py
pipyadc/utils/__init__.py
pipyadc/utils/text_screen.py
pipyadc-2.1.dist-info/LICENSE
pipyadc-2.1.dist-info/METADATA
pipyadc-2.1.dist-info/WHEEL
pipyadc-2.1.dist-info/top_level.txt
pipyadc-2.1.dist-info/RECORD
