Metadata-Version: 2.1
Name: pipyadc
Version: 2.1
Summary: Python package for interfacing Texas Instruments ADS1255 and ADS1256 SPI bus based ADCs with the Raspberry Pi
Home-page: https://github.com/ul-gh/PiPyADC
Author: Ulrich Lukas
Maintainer: Ulrich Lukas
Maintainer-email: ul-gh@datenparkplatz.de
Classifier: Programming Language :: Python :: 3
Classifier: License :: OSI Approved :: GNU Lesser General Public License v2 (LGPLv2)
Classifier: Operating System :: POSIX :: Linux
Requires-Python: >=3
License-File: LICENSE
Requires-Dist: pigpio
